api/__init__.py
api/api.py
pypercraft/__init__.py
pypercraft/prompts.py
pypercraft/pypercraft.py
tests/__init__.py
tests/test_api.py
tests/test_pypercraft.py
pypercraft-0.1.5.dist-info/LICENSE
pypercraft-0.1.5.dist-info/METADATA
pypercraft-0.1.5.dist-info/WHEEL
pypercraft-0.1.5.dist-info/top_level.txt
pypercraft-0.1.5.dist-info/RECORD
