Metadata-Version: 2.1
Name: pypercraft
Version: 0.1.5
Summary: Utilize Large Language Models to Craft Papers and Export them to Documents
Author: alkhalifas
License-File: LICENSE
Requires-Dist: fastapi
Requires-Dist: langchain
Requires-Dist: openai
Requires-Dist: uvicorn
Requires-Dist: pylint
Requires-Dist: httpx
Requires-Dist: streamlit
Requires-Dist: python-docx
